vtk_u3dexporter-0.3.0.data/data/include/vtku3dexporter-0.1/vtkU3DExporter.h
vtk_u3dexporter-0.3.0.data/data/include/vtku3dexporter-0.1/vtkU3DExporterModule.h
vtk_u3dexporter-0.3.0.data/data/lib/cmake/vtk/vtkU3DExporter-targets-release.cmake
vtk_u3dexporter-0.3.0.data/data/lib/cmake/vtk/vtkU3DExporter-targets.cmake
vtk_u3dexporter-0.3.0.data/data/lib/cmake/vtk/vtkU3DExporter-vtk-module-find-packages.cmake
vtk_u3dexporter-0.3.0.data/data/lib/cmake/vtk/vtkU3DExporter-vtk-module-properties.cmake
vtk_u3dexporter-0.3.0.data/data/lib/cmake/vtk/vtkmodules-vtk-python-module-properties.cmake
vtk_u3dexporter-0.3.0.data/data/lib/vtk/hierarchy/vtkU3DExporter/vtkU3DExporter-hierarchy.txt
vtkmodules/libIDTF.so
vtkmodules/libIFXCore.so
vtkmodules/libIFXExporting.so
vtkmodules/libIFXImporting.so
vtkmodules/libIFXScheduling.so
vtkmodules/libvtkU3DExporter.so
vtkmodules/libvtkU3DExporter.so.0.1.0
vtkmodules/libvtkU3DExporter.so.1
vtkmodules/vtkU3DExporter.cpython-38-x86_64-linux-gnu.so
vtkmodules/__pyinstaller_vtkU3DExporter/__init__.py
vtkmodules/__pyinstaller_vtkU3DExporter/hook-vtk.py
vtk_u3dexporter-0.3.0.dist-info/LICENSE
vtk_u3dexporter-0.3.0.dist-info/METADATA
vtk_u3dexporter-0.3.0.dist-info/WHEEL
vtk_u3dexporter-0.3.0.dist-info/entry_points.txt
vtk_u3dexporter-0.3.0.dist-info/top_level.txt
vtk_u3dexporter-0.3.0.dist-info/RECORD
