Metadata-Version: 2.1
Name: vtk-u3dexporter
Version: 0.3.0
Summary: General-purpose features that may be integrated into VTK library in the future.
Home-page: https://github.com/ClinicalGraphics/VTKU3DExporter
Author: Jean-Christophe Fillion-Robin
License: Apache Software License
Project-URL: Bug Reports, https://github.com/ClinicalGraphics/VTKU3DExporter/issues
Project-URL: Source, https://github.com/ClinicalGraphics/VTKU3DExporter/
Classifier: Development Status :: 4 - Beta
Classifier: License :: OSI Approved :: Apache Software License
Classifier: Programming Language :: Python :: 3
Classifier: Topic :: Scientific/Engineering :: Medical Science Apps.
License-File: LICENSE
Requires-Dist: vtk ==9.2.5
